json_dict_diff.py
json_dict_diff-1.0.5.dist-info/METADATA
json_dict_diff-1.0.5.dist-info/WHEEL
json_dict_diff-1.0.5.dist-info/licenses/LICENCE
json_dict_diff-1.0.5.dist-info/RECORD
