Metadata-Version: 2.3
Name: json_dict_diff
Version: 1.0.5
Summary: A simple library to create a minimal diff of two json compatible dictionaries
Project-URL: Homepage, https://github.com/g3rrit/json_dict_diff
Project-URL: Issues, https://github.com/g3rrit/json_dict_diff/issues
Author-email: Gerrit Proessl <gerrit.proessl@gmail.com>
License-File: LICENCE
Classifier: License :: OSI Approved :: MIT License
Classifier: Operating System :: OS Independent
Classifier: Programming Language :: Python :: 3
Requires-Python: >=3.9
